Workbook

Sheet Portada
B4: S I S T E M A D E G E S T I Ó N
B6: Gestión de Proyectos
B9: Plantilla integral: plan, cronograma, riesgos, presupuesto y control
B11: Jesús González · https://jesus-site-silk.vercel.app/
B15: IDENTIFICACIÓN DEL PROYECTO
B16: Nombre del proyecto | C16: Implementación de plataforma analítica
B17: Cliente / Área | C17: Dirección de Operaciones
B18: Líder de proyecto | C18: Jesús González
B19: Patrocinador | C19: Nombre del patrocinador
B20: Fecha de inicio | C20: 46234
B21: Fecha de cierre planeada | C21: 46354
B22: Versión del documento | C22: 1,0
B24: CONTENIDO DEL LIBRO
B25: Dashboard | C25: Indicadores del proyecto calculados automáticamente
B26: Ficha del Proyecto | C26: Acta constitutiva: objetivo, alcance, criterios de éxito
B27: Plan de Tareas | C27: Desglose de trabajo con responsables, fechas y avance
B28: Cronograma | C28: Diagrama de Gantt semanal, alimentado del Plan de Tareas
B29: Hitos | C29: Puntos de control y entregables comprometidos
B30: Riesgos | C30: Matriz de riesgos con severidad y plan de mitigación
B31: Interesados | C31: Mapa de poder e interés con estrategia por actor
B32: Presupuesto | C32: Presupuesto planeado contra ejercido, por categoría
B33: Equipo | C33: Roles, asignación y costo por recurso
B34: Decisiones | C34: Bitácora de decisiones tomadas y su justificación
B35: Incidencias | C35: Registro de problemas abiertos y su resolución
B36: Listas | C36: Catálogos que alimentan las listas desplegables
B38: CÓMO USAR ESTA PLANTILLA
B39: Celdas con fondo crema y texto azul | C39: Son las únicas que debes editar. Todo lo demás se calcula solo.
B40: Celdas con texto negro | C40: Contienen fórmulas. Si las sobrescribes, se rompe el Dashboard.
B41: Hoja Listas | C41: Edita ahí los catálogos (fases, responsables, categorías) antes de capturar.
B42: Fila de ejemplo | C42: Cada hoja incluye una fila de muestra en gris. Bórrala cuando empieces.
B43: Orden sugerido | C43: Ficha → Equipo → Listas → Plan de Tareas → Riesgos → Presupuesto.
B45: Plantilla desarrollada por Jesús González · https://jesus-site-silk.vercel.app/

Sheet Dashboard
A1: DASHBOARD DEL PROYECTO
A2: Todo se calcula automáticamente. No captures nada en esta hoja.
A3: Jesús González · https://jesus-site-silk.vercel.app/
B6: AVANCE GENERAL
B8: TAREAS REGISTRADAS | E8: AVANCE PROMEDIO | H8: TAREAS COMPLETADAS
B9: =COUNTIF('Plan de Tareas'!$C$7:$C$126,"?*") -> 2 | E9: =IFERROR(SUMPRODUCT(('Plan de Tareas'!$C$7:$C$126<>"")*('Plan de Tareas'!$I$7:$I$126))/COUNTIF('Plan de Tareas'!$C$7:$C$126,"?*"),0) -> 0.3 | H9: =COUNTIF('Plan de Tareas'!$J$7:$J$126,"Completada") -> 0
B11: EN CURSO | E11: VENCIDAS | H11: POR VENCER (3 DÍAS)
B12: =COUNTIF('Plan de Tareas'!$J$7:$J$126,"En curso") -> 1 | E12: =COUNTIF('Plan de Tareas'!$L$7:$L$126,"Vencida") -> 0 | H12: =COUNTIF('Plan de Tareas'!$L$7:$L$126,"Por vencer") -> 0
B15: RIESGOS E INCIDENCIAS
B17: RIESGOS ABIERTOS | E17: RIESGOS CRÍTICOS O ALTOS | H17: INCIDENCIAS ABIERTAS
B18: =COUNTIF(Riesgos!$L$7:$L$47,"Abierto")+COUNTIF(Riesgos!$L$7:$L$47,"En mitigación") -> 1 | E18: =COUNTIF(Riesgos!$G$7:$G$47,"Crítico")+COUNTIF(Riesgos!$G$7:$G$47,"Alto") -> 1 | H18: =COUNTIF(Incidencias!$H$7:$H$37,"Abierta")+COUNTIF(Incidencias!$H$7:$H$37,"En análisis") -> 1
B21: HITOS Y PRESUPUESTO
B23: HITOS CUMPLIDOS | E23: HITOS VENCIDOS | H23: % PRESUPUESTO EJECUTADO
B24: =COUNTIF(Hitos!$G$7:$G$37,"Cumplido")+COUNTIF(Hitos!$G$7:$G$37,"Cumplido con retraso") -> 0 | E24: =COUNTIF(Hitos!$G$7:$G$37,"Vencido") -> 0 | H24: =IFERROR((Presupuesto!$F$43+Presupuesto!$G$43)/Presupuesto!$E$43,0) -> 0.25
B27: DISTRIBUCIÓN POR ESTADO
B28: Estado | C28: Tareas | D28: % del total | E28: Fase | F28: Tareas | G28: Avance | H28: Categoría | I28: Planeado | J28: Ejercido
B29: No iniciada | C29: =COUNTIF('Plan de Tareas'!$J$7:$J$126,"No iniciada") -> 1 | D29: =IFERROR($C29/COUNTIF('Plan de Tareas'!$C$7:$C$126,"?*"),0) -> 0.5 | E29: Inicio | F29: =COUNTIF('Plan de Tareas'!$B$7:$B$126,"Inicio") -> 0 | G29: =IFERROR(SUMIF('Plan de Tareas'!$B$7:$B$126,"Inicio",'Plan de Tareas'!$I$7:$I$126)/$F29,0) -> 0 | H29: Personal | I29: =SUMIF(Presupuesto!$C$7:$C$42,"Personal",Presupuesto!$E$7:$E$42) -> 0 | J29: =SUMIF(Presupuesto!$C$7:$C$42,"Personal",Presupuesto!$F$7:$F$42) -> 0
B30: En curso | C30: =COUNTIF('Plan de Tareas'!$J$7:$J$126,"En curso") -> 1 | D30: =IFERROR($C30/COUNTIF('Plan de Tareas'!$C$7:$C$126,"?*"),0) -> 0.5 | E30: Planeación | F30: =COUNTIF('Plan de Tareas'!$B$7:$B$126,"Planeación") -> 1 | G30: =IFERROR(SUMIF('Plan de Tareas'!$B$7:$B$126,"Planeación",'Plan de Tareas'!$I$7:$I$126)/$F30,0) -> 0.6 | H30: Licencias | I30: =SUMIF(Presupuesto!$C$7:$C$42,"Licencias",Presupuesto!$E$7:$E$42) -> 480000 | J30: =SUMIF(Presupuesto!$C$7:$C$42,"Licencias",Presupuesto!$F$7:$F$42) -> 120000
B31: Bloqueada | C31: =COUNTIF('Plan de Tareas'!$J$7:$J$126,"Bloqueada") -> 0 | D31: =IFERROR($C31/COUNTIF('Plan de Tareas'!$C$7:$C$126,"?*"),0) -> 0 | E31: Diseño | F31: =COUNTIF('Plan de Tareas'!$B$7:$B$126,"Diseño") -> 1 | G31: =IFERROR(SUMIF('Plan de Tareas'!$B$7:$B$126,"Diseño",'Plan de Tareas'!$I$7:$I$126)/$F31,0) -> 0 | H31: Infraestructura | I31: =SUMIF(Presupuesto!$C$7:$C$42,"Infraestructura",Presupuesto!$E$7:$E$42) -> 0 | J31: =SUMIF(Presupuesto!$C$7:$C$42,"Infraestructura",Presupuesto!$F$7:$F$42) -> 0
B32: Completada | C32: =COUNTIF('Plan de Tareas'!$J$7:$J$126,"Completada") -> 0 | D32: =IFERROR($C32/COUNTIF('Plan de Tareas'!$C$7:$C$126,"?*"),0) -> 0 | E32: Construcción | F32: =COUNTIF('Plan de Tareas'!$B$7:$B$126,"Construcción") -> 0 | G32: =IFERROR(SUMIF('Plan de Tareas'!$B$7:$B$126,"Construcción",'Plan de Tareas'!$I$7:$I$126)/$F32,0) -> 0 | H32: Consultoría | I32: =SUMIF(Presupuesto!$C$7:$C$42,"Consultoría",Presupuesto!$E$7:$E$42) -> 0 | J32: =SUMIF(Presupuesto!$C$7:$C$42,"Consultoría",Presupuesto!$F$7:$F$42) -> 0
B33: Cancelada | C33: =COUNTIF('Plan de Tareas'!$J$7:$J$126,"Cancelada") -> 0 | D33: =IFERROR($C33/COUNTIF('Plan de Tareas'!$C$7:$C$126,"?*"),0) -> 0 | E33: Pruebas | F33: =COUNTIF('Plan de Tareas'!$B$7:$B$126,"Pruebas") -> 0 | G33: =IFERROR(SUMIF('Plan de Tareas'!$B$7:$B$126,"Pruebas",'Plan de Tareas'!$I$7:$I$126)/$F33,0) -> 0 | H33: Capacitación | I33: =SUMIF(Presupuesto!$C$7:$C$42,"Capacitación",Presupuesto!$E$7:$E$42) -> 0 | J33: =SUMIF(Presupuesto!$C$7:$C$42,"Capacitación",Presupuesto!$F$7:$F$42) -> 0
E34: Despliegue | F34: =COUNTIF('Plan de Tareas'!$B$7:$B$126,"Despliegue") -> 0 | G34: =IFERROR(SUMIF('Plan de Tareas'!$B$7:$B$126,"Despliegue",'Plan de Tareas'!$I$7:$I$126)/$F34,0) -> 0 | H34: Viáticos | I34: =SUMIF(Presupuesto!$C$7:$C$42,"Viáticos",Presupuesto!$E$7:$E$42) -> 0 | J34: =SUMIF(Presupuesto!$C$7:$C$42,"Viáticos",Presupuesto!$F$7:$F$42) -> 0
E35: Cierre | F35: =COUNTIF('Plan de Tareas'!$B$7:$B$126,"Cierre") -> 0 | G35: =IFERROR(SUMIF('Plan de Tareas'!$B$7:$B$126,"Cierre",'Plan de Tareas'!$I$7:$I$126)/$F35,0) -> 0 | H35: Otros | I35: =SUMIF(Presupuesto!$C$7:$C$42,"Otros",Presupuesto!$E$7:$E$42) -> 0 | J35: =SUMIF(Presupuesto!$C$7:$C$42,"Otros",Presupuesto!$F$7:$F$42) -> 0
B38: Jesús González · https://jesus-site-silk.vercel.app/ · Los indicadores se recalculan al abrir el archivo (F9 para forzar).

Sheet Ficha del Proyecto
A1: FICHA DEL PROYECTO
A2: Acta constitutiva. Llénala antes que nada: es el contrato de lo que se va a hacer.
A3: Jesús González · https://jesus-site-silk.vercel.app/
B6: DEFINICIÓN
B7: Problema u oportunidad
B8: Objetivo del proyecto
B9: Beneficio esperado
B11: ALCANCE
B12: Sí incluye
B13: NO incluye
B14: Supuestos
B15: Restricciones
B17: GOBIERNO
B18: Patrocinador
B19: Líder de proyecto
... B27: Definición de terminado

Sheet Plan de Tareas
A1: PLAN DE TAREAS
A2: El corazón del libro. El Dashboard y el Cronograma se alimentan de esta hoja.
A3: Jesús González · https://jesus-site-silk.vercel.app/
A6: ID | B6: Fase | C6: Tarea / Entregable | D6: Responsable | E6: Prioridad | F6: Inicio plan | G6: Fin plan | H6: Días | I6: % Avance | J6: Estado | K6: Días al vencimiento | L6: Semáforo | M6: Depende de | N6: Notas
A7: =IF($C7="","",ROW()-6) -> 1 | B7: Planeación | C7: Levantamiento de requerimientos con negocio | D7: Jesús González | E7: Alta | F7: 46234 | G7: 46244 | H7: =IF(OR($C7="",$F7="",$G7=""),"",$G7-$F7+1) -> 11 | I7: 0.6 | J7: En curso | K7: =IF(OR($C7="",$G7=""),"",IF(OR($J7="Completada",$J7="Cancelada"),"-",$G7-TODAY())) -> 11 | L7: =IF($C7="","",IF($J7="Completada","Completada",IF($J7="Cancelada","Cancelada",IF($J7="Bloqueada","Bloqueada",IF($G7="","Sin fecha",IF($G7<TODAY(),"Vencida",IF($G7-TODAY()<=3,"Por vencer","En tiempo"))))))) -> En tiempo | N7: Sesiones con las 3 áreas usuarias
A8: =IF($C8="","",ROW()-6) -> 2 | B8: Diseño | C8: Diseño del modelo de datos | D8: Recurso 2 | E8: Alta | F8: 46245 | G8: 46259 | H8: =IF(OR($C8="",$F8="",$G8=""),"",$G8-$F8+1) -> 15 | I8: 0 | J8: No iniciada | K8: =IF(OR($C8="",$G8=""),"",IF(OR($J8="Completada",$J8="Cancelada"),"-",$G8-TODAY())) -> 26 | L8: =IF($C8="","",IF($J8="Completada","Completada",IF($J8="Cancelada","Cancelada",IF($J8="Bloqueada","Bloqueada",IF($G8="","Sin fecha",IF($G8<TODAY(),"Vencida",IF($G8-TODAY()<=3,"Por vencer","En tiempo"))))))) -> En tiempo | M8: 1 | N8: Depende del cierre de requerimientos
A9: =IF($C9="","",ROW()-6) | H9: =IF(OR($C9="",$F9="",$G9=""),"",$G9-$F9+1) | K9: =IF(OR($C9="",$G9=""),"",IF(OR($J9="Completada",$J9="Cancelada"),"-",$G9-TODAY())) | L9: =IF($C9="","",IF($J9="Completada","Completada",IF($J9="Cancelada","Cancelada",IF($J9="Bloqueada","Bloqueada",IF($G9="","Sin fecha",IF($G9<TODAY(),"Vencida",IF($G9-TODAY()<=3,"Por vencer","En tiempo")))))))
A10: =IF($C10="","",ROW()-6) | H10: =IF(OR($C10="",$F10="",$G10=""),"",$G10-$F10+1) | K10: =IF(OR($C10="",$G10=""),"",IF(OR($J10="Completada",$J10="Cancelada"),"-",$G10-TODAY())) | L10: =IF($C10="","",IF($J10="Completada","Completada",IF($J10="Cancelada","Cancelada",IF($J10="Bloqueada","Bloqueada",IF($G10="","Sin fecha",IF($G10<TODAY(),"Vencida",IF($G10-TODAY()<=3,"Por vencer","En tiempo")))))))
A11: =IF($C11="","",ROW()-6) | H11: =IF(OR($C11="",$F11="",$G11=""),"",$G11-$F11+1) | K11: =IF(OR($C11="",$G11=""),"",IF(OR($J11="Completada",$J11="Cancelada"),"-",$G11-TODAY())) | L11: =IF($C11="","",IF($J11="Completada","Completada",IF($J11="Cancelada","Cancelada",IF($J11="Bloqueada","Bloqueada",IF($G11="","Sin fecha",IF($G11<TODAY(),"Vencida",IF($G11-TODAY()<=3,"Por vencer","En tiempo")))))))
A12: =IF($C12="","",ROW()-6) | H12: =IF(OR($C12="",$F12="",$G12=""),"",$G12-$F12+1) | K12: =IF(OR($C12="",$G12=""),"",IF(OR($J12="Completada",$J12="Cancelada"),"-",$G12-TODAY())) | L12: =IF($C12="","",IF($J12="Completada","Completada",IF($J12="Cancelada","Cancelada",IF($J12="Bloqueada","Bloqueada",IF($G12="","Sin fecha",IF($G12<TODAY(),"Vencida",IF($G12-TODAY()<=3,"Por vencer","En tiempo")))))))
A13: =IF($C13="","",ROW()-6) | H13: =IF(OR($C13="",$F13="",$G13=""),"",$G13-$F13+1) | K13: =IF(OR($C13="",$G13=""),"",IF(OR($J13="Completada",$J13="Cancelada"),"-",$G13-TODAY())) | L13: =IF($C13="","",IF($J13="Completada","Completada",IF($J13="Cancelada","Cancelada",IF($J13="Bloqueada","Bloqueada",IF($G13="","Sin fecha",IF($G13<TODAY(),"Vencida",IF($G13-TODAY()<=3,"Por vencer","En tiempo")))))))
A14: =IF($C14="","",ROW()-6) | H14: =IF(OR($C14="",$F14="",$G14=""),"",$G14-$F14+1) | K14: =IF(OR($C14="",$G14=""),"",IF(OR($J14="Completada",$J14="Cancelada"),"-",$G14-TODAY())) | L14: =IF($C14="","",IF($J14="Completada","Completada",IF($J14="Cancelada","Cancelada",IF($J14="Bloqueada","Bloqueada",IF($G14="","Sin fecha",IF($G14<TODAY(),"Vencida",IF($G14-TODAY()<=3,"Por vencer","En tiempo")))))))
A15: =IF($C15="","",ROW()-6) | H15: =IF(OR($C15="",$F15="",$G15=""),"",$G15-$F15+1) | K15: =IF(OR($C15="",$G15=""),"",IF(OR($J15="Completada",$J15="Cancelada"),"-",$G15-TODAY())) | L15: =IF($C15="","",IF($J15="Completada","Completada",IF($J15="Cancelada","Cancelada",IF($J15="Bloqueada","Bloqueada",IF($G15="","Sin fecha",IF($G15<TODAY(),"Vencida",IF($G15-TODAY()<=3,"Por vencer","En tiempo")))))))
A16: =IF($C16="","",ROW()-6) | H16: =IF(OR($C16="",$F16="",$G16=""),"",$G16-$F16+1) | K16: =IF(OR($C16="",$G16=""),"",IF(OR($J16="Completada",$J16="Cancelada"),"-",$G16-TODAY())) | L16: =IF($C16="","",IF($J16="Completada","Completada",IF($J16="Cancelada","Cancelada",IF($J16="Bloqueada","Bloqueada",IF($G16="","Sin fecha",IF($G16<TODAY(),"Vencida",IF($G16-TODAY()<=3,"Por vencer","En tiempo")))))))
A17: =IF($C17="","",ROW()-6) | H17: =IF(OR($C17="",$F17="",$G17=""),"",$G17-$F17+1) | K17: =IF(OR($C17="",$G17=""),"",IF(OR($J17="Completada",$J17="Cancelada"),"-",$G17-TODAY())) | L17: =IF($C17="","",IF($J17="Completada","Completada",IF($J17="Cancelada","Cancelada",IF($J17="Bloqueada","Bloqueada",IF($G17="","Sin fecha",IF($G17<TODAY(),"Vencida",IF($G17-TODAY()<=3,"Por vencer","En tiempo")))))))
A18: =IF($C18="","",ROW()-6) | H18: =IF(OR($C18="",$F18="",$G18=""),"",$G18-$F18+1) | K18: =IF(OR($C18="",$G18=""),"",IF(OR($J18="Completada",$J18="Cancelada"),"-",$G18-TODAY())) | L18: =IF($C18="","",IF($J18="Completada","Completada",IF($J18="Cancelada","Cancelada",IF($J18="Bloqueada","Bloqueada",IF($G18="","Sin fecha",IF($G18<TODAY(),"Vencida",IF($G18-TODAY()<=3,"Por vencer","En tiempo")))))))
A19: =IF($C19="","",ROW()-6) | H19: =IF(OR($C19="",$F19="",$G19=""),"",$G19-$F19+1) | K19: =IF(OR($C19="",$G19=""),"",IF(OR($J19="Completada",$J19="Cancelada"),"-",$G19-TODAY())) | L19: =IF($C19="","",IF($J19="Completada","Completada",IF($J19="Cancelada","Cancelada",IF($J19="Bloqueada","Bloqueada",IF($G19="","Sin fecha",IF($G19<TODAY(),"Vencida",IF($G19-TODAY()<=3,"Por vencer","En tiempo")))))))
A20: =IF($C20="","",ROW()-6) | H20: =IF(OR($C20="",$F20="",$G20=""),"",$G20-$F20+1) | K20: =IF(OR($C20="",$G20=""),"",IF(OR($J20="Completada",$J20="Cancelada"),"-",$G20-TODAY())) | L20: =IF($C20="","",IF($J20="Completada","Completada",IF($J20="Cancelada","Cancelada",IF($J20="Bloqueada","Bloqueada",IF($G20="","Sin fecha",IF($G20<TODAY(),"Vencida",IF($G20-TODAY()<=3,"Por vencer","En tiempo")))))))
... A126: =IF($C126="","",ROW()-6) | H126: =IF(OR($C126="",$F126="",$G126=""),"",$G126-$F126+1) | K126: =IF(OR($C126="",$G126=""),"",IF(OR($J126="Completada",$J126="Cancelada"),"-",$G126-TODAY())) | L126: =IF($C126="","",IF($J126="Completada","Completada",IF($J126="Cancelada","Cancelada",IF($J126="Bloqueada","Bloqueada",IF($G126="","Sin fecha",IF($G126<TODAY(),"Vencida",IF($G126-TODAY()<=3,"Por vencer","En tiempo")))))))

Sheet Cronograma
A1: CRONOGRAMA (GANTT)
A2: Se dibuja solo a partir del Plan de Tareas. Solo captura la fecha de arranque en C5.
A3: Jesús González · https://jesus-site-silk.vercel.app/
A5: Semana 1 inicia: | C5: 46230
A7: ID | B7: Tarea | C7: Responsable | D7: Inicio | E7: Fin | F7: =$C$5+0 -> 46230 | G7: =$C$5+7 -> 46237 | H7: =$C$5+14 -> 46244 | I7: =$C$5+21 -> 46251 | J7: =$C$5+28 -> 46258 | K7: =$C$5+35 -> 46265 | L7: =$C$5+42 -> 46272 | M7: =$C$5+49 -> 46279 | N7: =$C$5+56 -> 46286 | O7: =$C$5+63 -> 46293 | P7: =$C$5+70 -> 46300 | Q7: =$C$5+77 -> 46307 | R7: =$C$5+84 -> 46314 | S7: =$C$5+91 -> 46321 | T7: =$C$5+98 -> 46328 | U7: =$C$5+105 -> 46335 | V7: =$C$5+112 -> 46342 | W7: =$C$5+119 -> 46349 | X7: =$C$5+126 -> 46356 | Y7: =$C$5+133 -> 46363 | Z7: =$C$5+140 -> 46370 | AA7: =$C$5+147 -> 46377 | AB7: =$C$5+154 -> 46384 | AC7: =$C$5+161 -> 46391 | AD7: =$C$5+168 -> 46398 | AE7: =$C$5+175 -> 46405
A8: =IF('Plan de Tareas'!$C7="","",'Plan de Tareas'!$A7) -> 1 | B8: =IF('Plan de Tareas'!$C7="","",'Plan de Tareas'!$C7) -> Levantamiento de requerimientos con negocio | C8: =IF('Plan de Tareas'!$C7="","",'Plan de Tareas'!$D7) -> Jesús González | D8: =IF('Plan de Tareas'!$F7="","",'Plan de Tareas'!$F7) -> 46234 | E8: =IF('Plan de Tareas'!$G7="","",'Plan de Tareas'!$G7) -> 46244 | F8: =IF(OR($D8="",$E8=""),"",IF(AND($D8<=F$7+6,$E8>=F$7),IF('Plan de Tareas'!$J7="Completada",2,1),"")) -> 1 | G8: =IF(OR($D8="",$E8=""),"",IF(AND($D8<=G$7+6,$E8>=G$7),IF('Plan de Tareas'!$J7="Completada",2,1),"")) -> 1 | H8: =IF(OR($D8="",$E8=""),"",IF(AND($D8<=H$7+6,$E8>=H$7),IF('Plan de Tareas'!$J7="Completada",2,1),"")) -> 1 | I8: =IF(OR($D8="",$E8=""),"",IF(AND($D8<=I$7+6,$E8>=I$7),IF('Plan de Tareas'!$J7="Completada",2,1),"")) | J8: =IF(OR($D8="",$E8=""),"",IF(AND($D8<=J$7+6,$E8>=J$7),IF('Plan de Tareas'!$J7="Completada",2,1),"")) | K8: =IF(OR($D8="",$E8=""),"",IF(AND($D8<=K$7+6,$E8>=K$7),IF('Plan de Tareas'!$J7="Completada",2,1),"")) | L8: =IF(OR($D8="",$E8=""),"",IF(AND($D8<=L$7+6,$E8>=L$7),IF('Plan de Tareas'!$J7="Completada",2,1),"")) | M8: =IF(OR($D8="",$E8=""),"",IF(AND($D8<=M$7+6,$E8>=M$7),IF('Plan de Tareas'!$J7="Completada",2,1),"")) | ... AE8: =IF(OR($D8="",$E8=""),"",IF(AND($D8<=AE$7+6,$E8>=AE$7),IF('Plan de Tareas'!$J7="Completada",2,1),""))
A9: =IF('Plan de Tareas'!$C8="","",'Plan de Tareas'!$A8) -> 2 | B9: =IF('Plan de Tareas'!$C8="","",'Plan de Tareas'!$C8) -> Diseño del modelo de datos | C9: =IF('Plan de Tareas'!$C8="","",'Plan de Tareas'!$D8) -> Recurso 2 | D9: =IF('Plan de Tareas'!$F8="","",'Plan de Tareas'!$F8) -> 46245 | E9: =IF('Plan de Tareas'!$G8="","",'Plan de Tareas'!$G8) -> 46259 | F9: =IF(OR($D9="",$E9=""),"",IF(AND($D9<=F$7+6,$E9>=F$7),IF('Plan de Tareas'!$J8="Completada",2,1),"")) | G9: =IF(OR($D9="",$E9=""),"",IF(AND($D9<=G$7+6,$E9>=G$7),IF('Plan de Tareas'!$J8="Completada",2,1),"")) | H9: =IF(OR($D9="",$E9=""),"",IF(AND($D9<=H$7+6,$E9>=H$7),IF('Plan de Tareas'!$J8="Completada",2,1),"")) -> 1 | I9: =IF(OR($D9="",$E9=""),"",IF(AND($D9<=I$7+6,$E9>=I$7),IF('Plan de Tareas'!$J8="Completada",2,1),"")) -> 1 | J9: =IF(OR($D9="",$E9=""),"",IF(AND($D9<=J$7+6,$E9>=J$7),IF('Plan de Tareas'!$J8="Completada",2,1),"")) -> 1 | K9: =IF(OR($D9="",$E9=""),"",IF(AND($D9<=K$7+6,$E9>=K$7),IF('Plan de Tareas'!$J8="Completada",2,1),"")) | L9: =IF(OR($D9="",$E9=""),"",IF(AND($D9<=L$7+6,$E9>=L$7),IF('Plan de Tareas'!$J8="Completada",2,1),"")) | M9: =IF(OR($D9="",$E9=""),"",IF(AND($D9<=M$7+6,$E9>=M$7),IF('Plan de Tareas'!$J8="Completada",2,1),"")) | ... AE9: =IF(OR($D9="",$E9=""),"",IF(AND($D9<=AE$7+6,$E9>=AE$7),IF('Plan de Tareas'!$J8="Completada",2,1),""))
A10: =IF('Plan de Tareas'!$C9="","",'Plan de Tareas'!$A9) | B10: =IF('Plan de Tareas'!$C9="","",'Plan de Tareas'!$C9) | C10: =IF('Plan de Tareas'!$C9="","",'Plan de Tareas'!$D9) | D10: =IF('Plan de Tareas'!$F9="","",'Plan de Tareas'!$F9) | E10: =IF('Plan de Tareas'!$G9="","",'Plan de Tareas'!$G9) | F10: =IF(OR($D10="",$E10=""),"",IF(AND($D10<=F$7+6,$E10>=F$7),IF('Plan de Tareas'!$J9="Completada",2,1),"")) | G10: =IF(OR($D10="",$E10=""),"",IF(AND($D10<=G$7+6,$E10>=G$7),IF('Plan de Tareas'!$J9="Completada",2,1),"")) | H10: =IF(OR($D10="",$E10=""),"",IF(AND($D10<=H$7+6,$E10>=H$7),IF('Plan de Tareas'!$J9="Completada",2,1),"")) | I10: =IF(OR($D10="",$E10=""),"",IF(AND($D10<=I$7+6,$E10>=I$7),IF('Plan de Tareas'!$J9="Completada",2,1),"")) | J10: =IF(OR($D10="",$E10=""),"",IF(AND($D10<=J$7+6,$E10>=J$7),IF('Plan de Tareas'!$J9="Completada",2,1),"")) | K10: =IF(OR($D10="",$E10=""),"",IF(AND($D10<=K$7+6,$E10>=K$7),IF('Plan de Tareas'!$J9="Completada",2,1),"")) | L10: =IF(OR($D10="",$E10=""),"",IF(AND($D10<=L$7+6,$E10>=L$7),IF('Plan de Tareas'!$J9="Completada",2,1),"")) | M10: =IF(OR($D10="",$E10=""),"",IF(AND($D10<=M$7+6,$E10>=M$7),IF('Plan de Tareas'!$J9="Completada",2,1),"")) | ... AE10: =IF(OR($D10="",$E10=""),"",IF(AND($D10<=AE$7+6,$E10>=AE$7),IF('Plan de Tareas'!$J9="Completada",2,1),""))
A11: =IF('Plan de Tareas'!$C10="","",'Plan de Tareas'!$A10) | B11: =IF('Plan de Tareas'!$C10="","",'Plan de Tareas'!$C10) | C11: =IF('Plan de Tareas'!$C10="","",'Plan de Tareas'!$D10) | D11: =IF('Plan de Tareas'!$F10="","",'Plan de Tareas'!$F10) | E11: =IF('Plan de Tareas'!$G10="","",'Plan de Tareas'!$G10) | F11: =IF(OR($D11="",$E11=""),"",IF(AND($D11<=F$7+6,$E11>=F$7),IF('Plan de Tareas'!$J10="Completada",2,1),"")) | G11: =IF(OR($D11="",$E11=""),"",IF(AND($D11<=G$7+6,$E11>=G$7),IF('Plan de Tareas'!$J10="Completada",2,1),"")) | H11: =IF(OR($D11="",$E11=""),"",IF(AND($D11<=H$7+6,$E11>=H$7),IF('Plan de Tareas'!$J10="Completada",2,1),"")) | I11: =IF(OR($D11="",$E11=""),"",IF(AND($D11<=I$7+6,$E11>=I$7),IF('Plan de Tareas'!$J10="Completada",2,1),"")) | J11: =IF(OR($D11="",$E11=""),"",IF(AND($D11<=J$7+6,$E11>=J$7),IF('Plan de Tareas'!$J10="Completada",2,1),"")) | K11: =IF(OR($D11="",$E11=""),"",IF(AND($D11<=K$7+6,$E11>=K$7),IF('Plan de Tareas'!$J10="Completada",2,1),"")) | L11: =IF(OR($D11="",$E11=""),"",IF(AND($D11<=L$7+6,$E11>=L$7),IF('Plan de Tareas'!$J10="Completada",2,1),"")) | M11: =IF(OR($D11="",$E11=""),"",IF(AND($D11<=M$7+6,$E11>=M$7),IF('Plan de Tareas'!$J10="Completada",2,1),"")) | ... AE11: =IF(OR($D11="",$E11=""),"",IF(AND($D11<=AE$7+6,$E11>=AE$7),IF('Plan de Tareas'!$J10="Completada",2,1),""))
A12: =IF('Plan de Tareas'!$C11="","",'Plan de Tareas'!$A11) | B12: =IF('Plan de Tareas'!$C11="","",'Plan de Tareas'!$C11) | C12: =IF('Plan de Tareas'!$C11="","",'Plan de Tareas'!$D11) | D12: =IF('Plan de Tareas'!$F11="","",'Plan de Tareas'!$F11) | E12: =IF('Plan de Tareas'!$G11="","",'Plan de Tareas'!$G11) | F12: =IF(OR($D12="",$E12=""),"",IF(AND($D12<=F$7+6,$E12>=F$7),IF('Plan de Tareas'!$J11="Completada",2,1),"")) | G12: =IF(OR($D12="",$E12=""),"",IF(AND($D12<=G$7+6,$E12>=G$7),IF('Plan de Tareas'!$J11="Completada",2,1),"")) | H12: =IF(OR($D12="",$E12=""),"",IF(AND($D12<=H$7+6,$E12>=H$7),IF('Plan de Tareas'!$J11="Completada",2,1),"")) | I12: =IF(OR($D12="",$E12=""),"",IF(AND($D12<=I$7+6,$E12>=I$7),IF('Plan de Tareas'!$J11="Completada",2,1),"")) | J12: =IF(OR($D12="",$E12=""),"",IF(AND($D12<=J$7+6,$E12>=J$7),IF('Plan de Tareas'!$J11="Completada",2,1),"")) | K12: =IF(OR($D12="",$E12=""),"",IF(AND($D12<=K$7+6,$E12>=K$7),IF('Plan de Tareas'!$J11="Completada",2,1),"")) | L12: =IF(OR($D12="",$E12=""),"",IF(AND($D12<=L$7+6,$E12>=L$7),IF('Plan de Tareas'!$J11="Completada",2,1),"")) | M12: =IF(OR($D12="",$E12=""),"",IF(AND($D12<=M$7+6,$E12>=M$7),IF('Plan de Tareas'!$J11="Completada",2,1),"")) | ... AE12: =IF(OR($D12="",$E12=""),"",IF(AND($D12<=AE$7+6,$E12>=AE$7),IF('Plan de Tareas'!$J11="Completada",2,1),""))
A13: =IF('Plan de Tareas'!$C12="","",'Plan de Tareas'!$A12) | B13: =IF('Plan de Tareas'!$C12="","",'Plan de Tareas'!$C12) | C13: =IF('Plan de Tareas'!$C12="","",'Plan de Tareas'!$D12) | D13: =IF('Plan de Tareas'!$F12="","",'Plan de Tareas'!$F12) | E13: =IF('Plan de Tareas'!$G12="","",'Plan de Tareas'!$G12) | F13: =IF(OR($D13="",$E13=""),"",IF(AND($D13<=F$7+6,$E13>=F$7),IF('Plan de Tareas'!$J12="Completada",2,1),"")) | G13: =IF(OR($D13="",$E13=""),"",IF(AND($D13<=G$7+6,$E13>=G$7),IF('Plan de Tareas'!$J12="Completada",2,1),"")) | H13: =IF(OR($D13="",$E13=""),"",IF(AND($D13<=H$7+6,$E13>=H$7),IF('Plan de Tareas'!$J12="Completada",2,1),"")) | I13: =IF(OR($D13="",$E13=""),"",IF(AND($D13<=I$7+6,$E13>=I$7),IF('Plan de Tareas'!$J12="Completada",2,1),"")) | J13: =IF(OR($D13="",$E13=""),"",IF(AND($D13<=J$7+6,$E13>=J$7),IF('Plan de Tareas'!$J12="Completada",2,1),"")) | K13: =IF(OR($D13="",$E13=""),"",IF(AND($D13<=K$7+6,$E13>=K$7),IF('Plan de Tareas'!$J12="Completada",2,1),"")) | L13: =IF(OR($D13="",$E13=""),"",IF(AND($D13<=L$7+6,$E13>=L$7),IF('Plan de Tareas'!$J12="Completada",2,1),"")) | M13: =IF(OR($D13="",$E13=""),"",IF(AND($D13<=M$7+6,$E13>=M$7),IF('Plan de Tareas'!$J12="Completada",2,1),"")) | ... AE13: =IF(OR($D13="",$E13=""),"",IF(AND($D13<=AE$7+6,$E13>=AE$7),IF('Plan de Tareas'!$J12="Completada",2,1),""))
A14: =IF('Plan de Tareas'!$C13="","",'Plan de Tareas'!$A13) | B14: =IF('Plan de Tareas'!$C13="","",'Plan de Tareas'!$C13) | C14: =IF('Plan de Tareas'!$C13="","",'Plan de Tareas'!$D13) | D14: =IF('Plan de Tareas'!$F13="","",'Plan de Tareas'!$F13) | E14: =IF('Plan de Tareas'!$G13="","",'Plan de Tareas'!$G13) | F14: =IF(OR($D14="",$E14=""),"",IF(AND($D14<=F$7+6,$E14>=F$7),IF('Plan de Tareas'!$J13="Completada",2,1),"")) | G14: =IF(OR($D14="",$E14=""),"",IF(AND($D14<=G$7+6,$E14>=G$7),IF('Plan de Tareas'!$J13="Completada",2,1),"")) | H14: =IF(OR($D14="",$E14=""),"",IF(AND($D14<=H$7+6,$E14>=H$7),IF('Plan de Tareas'!$J13="Completada",2,1),"")) | I14: =IF(OR($D14="",$E14=""),"",IF(AND($D14<=I$7+6,$E14>=I$7),IF('Plan de Tareas'!$J13="Completada",2,1),"")) | J14: =IF(OR($D14="",$E14=""),"",IF(AND($D14<=J$7+6,$E14>=J$7),IF('Plan de Tareas'!$J13="Completada",2,1),"")) | K14: =IF(OR($D14="",$E14=""),"",IF(AND($D14<=K$7+6,$E14>=K$7),IF('Plan de Tareas'!$J13="Completada",2,1),"")) | L14: =IF(OR($D14="",$E14=""),"",IF(AND($D14<=L$7+6,$E14>=L$7),IF('Plan de Tareas'!$J13="Completada",2,1),"")) | M14: =IF(OR($D14="",$E14=""),"",IF(AND($D14<=M$7+6,$E14>=M$7),IF('Plan de Tareas'!$J13="Completada",2,1),"")) | ... AE14: =IF(OR($D14="",$E14=""),"",IF(AND($D14<=AE$7+6,$E14>=AE$7),IF('Plan de Tareas'!$J13="Completada",2,1),""))
A15: =IF('Plan de Tareas'!$C14="","",'Plan de Tareas'!$A14) | B15: =IF('Plan de Tareas'!$C14="","",'Plan de Tareas'!$C14) | C15: =IF('Plan de Tareas'!$C14="","",'Plan de Tareas'!$D14) | D15: =IF('Plan de Tareas'!$F14="","",'Plan de Tareas'!$F14) | E15: =IF('Plan de Tareas'!$G14="","",'Plan de Tareas'!$G14) | F15: =IF(OR($D15="",$E15=""),"",IF(AND($D15<=F$7+6,$E15>=F$7),IF('Plan de Tareas'!$J14="Completada",2,1),"")) | G15: =IF(OR($D15="",$E15=""),"",IF(AND($D15<=G$7+6,$E15>=G$7),IF('Plan de Tareas'!$J14="Completada",2,1),"")) | H15: =IF(OR($D15="",$E15=""),"",IF(AND($D15<=H$7+6,$E15>=H$7),IF('Plan de Tareas'!$J14="Completada",2,1),"")) | I15: =IF(OR($D15="",$E15=""),"",IF(AND($D15<=I$7+6,$E15>=I$7),IF('Plan de Tareas'!$J14="Completada",2,1),"")) | J15: =IF(OR($D15="",$E15=""),"",IF(AND($D15<=J$7+6,$E15>=J$7),IF('Plan de Tareas'!$J14="Completada",2,1),"")) | K15: =IF(OR($D15="",$E15=""),"",IF(AND($D15<=K$7+6,$E15>=K$7),IF('Plan de Tareas'!$J14="Completada",2,1),"")) | L15: =IF(OR($D15="",$E15=""),"",IF(AND($D15<=L$7+6,$E15>=L$7),IF('Plan de Tareas'!$J14="Completada",2,1),"")) | M15: =IF(OR($D15="",$E15=""),"",IF(AND($D15<=M$7+6,$E15>=M$7),IF('Plan de Tareas'!$J14="Completada",2,1),"")) | ... AE15: =IF(OR($D15="",$E15=""),"",IF(AND($D15<=AE$7+6,$E15>=AE$7),IF('Plan de Tareas'!$J14="Completada",2,1),""))
A16: =IF('Plan de Tareas'!$C15="","",'Plan de Tareas'!$A15) | B16: =IF('Plan de Tareas'!$C15="","",'Plan de Tareas'!$C15) | C16: =IF('Plan de Tareas'!$C15="","",'Plan de Tareas'!$D15) | D16: =IF('Plan de Tareas'!$F15="","",'Plan de Tareas'!$F15) | E16: =IF('Plan de Tareas'!$G15="","",'Plan de Tareas'!$G15) | F16: =IF(OR($D16="",$E16=""),"",IF(AND($D16<=F$7+6,$E16>=F$7),IF('Plan de Tareas'!$J15="Completada",2,1),"")) | G16: =IF(OR($D16="",$E16=""),"",IF(AND($D16<=G$7+6,$E16>=G$7),IF('Plan de Tareas'!$J15="Completada",2,1),"")) | H16: =IF(OR($D16="",$E16=""),"",IF(AND($D16<=H$7+6,$E16>=H$7),IF('Plan de Tareas'!$J15="Completada",2,1),"")) | I16: =IF(OR($D16="",$E16=""),"",IF(AND($D16<=I$7+6,$E16>=I$7),IF('Plan de Tareas'!$J15="Completada",2,1),"")) | J16: =IF(OR($D16="",$E16=""),"",IF(AND($D16<=J$7+6,$E16>=J$7),IF('Plan de Tareas'!$J15="Completada",2,1),"")) | K16: =IF(OR($D16="",$E16=""),"",IF(AND($D16<=K$7+6,$E16>=K$7),IF('Plan de Tareas'!$J15="Completada",2,1),"")) | L16: =IF(OR($D16="",$E16=""),"",IF(AND($D16<=L$7+6,$E16>=L$7),IF('Plan de Tareas'!$J15="Completada",2,1),"")) | M16: =IF(OR($D16="",$E16=""),"",IF(AND($D16<=M$7+6,$E16>=M$7),IF('Plan de Tareas'!$J15="Completada",2,1),"")) | ... AE16: =IF(OR($D16="",$E16=""),"",IF(AND($D16<=AE$7+6,$E16>=AE$7),IF('Plan de Tareas'!$J15="Completada",2,1),""))
A17: =IF('Plan de Tareas'!$C16="","",'Plan de Tareas'!$A16) | B17: =IF('Plan de Tareas'!$C16="","",'Plan de Tareas'!$C16) | C17: =IF('Plan de Tareas'!$C16="","",'Plan de Tareas'!$D16) | D17: =IF('Plan de Tareas'!$F16="","",'Plan de Tareas'!$F16) | E17: =IF('Plan de Tareas'!$G16="","",'Plan de Tareas'!$G16) | F17: =IF(OR($D17="",$E17=""),"",IF(AND($D17<=F$7+6,$E17>=F$7),IF('Plan de Tareas'!$J16="Completada",2,1),"")) | G17: =IF(OR($D17="",$E17=""),"",IF(AND($D17<=G$7+6,$E17>=G$7),IF('Plan de Tareas'!$J16="Completada",2,1),"")) | H17: =IF(OR($D17="",$E17=""),"",IF(AND($D17<=H$7+6,$E17>=H$7),IF('Plan de Tareas'!$J16="Completada",2,1),"")) | I17: =IF(OR($D17="",$E17=""),"",IF(AND($D17<=I$7+6,$E17>=I$7),IF('Plan de Tareas'!$J16="Completada",2,1),"")) | J17: =IF(OR($D17="",$E17=""),"",IF(AND($D17<=J$7+6,$E17>=J$7),IF('Plan de Tareas'!$J16="Completada",2,1),"")) | K17: =IF(OR($D17="",$E17=""),"",IF(AND($D17<=K$7+6,$E17>=K$7),IF('Plan de Tareas'!$J16="Completada",2,1),"")) | L17: =IF(OR($D17="",$E17=""),"",IF(AND($D17<=L$7+6,$E17>=L$7),IF('Plan de Tareas'!$J16="Completada",2,1),"")) | M17: =IF(OR($D17="",$E17=""),"",IF(AND($D17<=M$7+6,$E17>=M$7),IF('Plan de Tareas'!$J16="Completada",2,1),"")) | ... AE17: =IF(OR($D17="",$E17=""),"",IF(AND($D17<=AE$7+6,$E17>=AE$7),IF('Plan de Tareas'!$J16="Completada",2,1),""))
A18: =IF('Plan de Tareas'!$C17="","",'Plan de Tareas'!$A17) | B18: =IF('Plan de Tareas'!$C17="","",'Plan de Tareas'!$C17) | C18: =IF('Plan de Tareas'!$C17="","",'Plan de Tareas'!$D17) | D18: =IF('Plan de Tareas'!$F17="","",'Plan de Tareas'!$F17) | E18: =IF('Plan de Tareas'!$G17="","",'Plan de Tareas'!$G17) | F18: =IF(OR($D18="",$E18=""),"",IF(AND($D18<=F$7+6,$E18>=F$7),IF('Plan de Tareas'!$J17="Completada",2,1),"")) | G18: =IF(OR($D18="",$E18=""),"",IF(AND($D18<=G$7+6,$E18>=G$7),IF('Plan de Tareas'!$J17="Completada",2,1),"")) | H18: =IF(OR($D18="",$E18=""),"",IF(AND($D18<=H$7+6,$E18>=H$7),IF('Plan de Tareas'!$J17="Completada",2,1),"")) | I18: =IF(OR($D18="",$E18=""),"",IF(AND($D18<=I$7+6,$E18>=I$7),IF('Plan de Tareas'!$J17="Completada",2,1),"")) | J18: =IF(OR($D18="",$E18=""),"",IF(AND($D18<=J$7+6,$E18>=J$7),IF('Plan de Tareas'!$J17="Completada",2,1),"")) | K18: =IF(OR($D18="",$E18=""),"",IF(AND($D18<=K$7+6,$E18>=K$7),IF('Plan de Tareas'!$J17="Completada",2,1),"")) | L18: =IF(OR($D18="",$E18=""),"",IF(AND($D18<=L$7+6,$E18>=L$7),IF('Plan de Tareas'!$J17="Completada",2,1),"")) | M18: =IF(OR($D18="",$E18=""),"",IF(AND($D18<=M$7+6,$E18>=M$7),IF('Plan de Tareas'!$J17="Completada",2,1),"")) | ... AE18: =IF(OR($D18="",$E18=""),"",IF(AND($D18<=AE$7+6,$E18>=AE$7),IF('Plan de Tareas'!$J17="Completada",2,1),""))
A19: =IF('Plan de Tareas'!$C18="","",'Plan de Tareas'!$A18) | B19: =IF('Plan de Tareas'!$C18="","",'Plan de Tareas'!$C18) | C19: =IF('Plan de Tareas'!$C18="","",'Plan de Tareas'!$D18) | D19: =IF('Plan de Tareas'!$F18="","",'Plan de Tareas'!$F18) | E19: =IF('Plan de Tareas'!$G18="","",'Plan de Tareas'!$G18) | F19: =IF(OR($D19="",$E19=""),"",IF(AND($D19<=F$7+6,$E19>=F$7),IF('Plan de Tareas'!$J18="Completada",2,1),"")) | G19: =IF(OR($D19="",$E19=""),"",IF(AND($D19<=G$7+6,$E19>=G$7),IF('Plan de Tareas'!$J18="Completada",2,1),"")) | H19: =IF(OR($D19="",$E19=""),"",IF(AND($D19<=H$7+6,$E19>=H$7),IF('Plan de Tareas'!$J18="Completada",2,1),"")) | I19: =IF(OR($D19="",$E19=""),"",IF(AND($D19<=I$7+6,$E19>=I$7),IF('Plan de Tareas'!$J18="Completada",2,1),"")) | J19: =IF(OR($D19="",$E19=""),"",IF(AND($D19<=J$7+6,$E19>=J$7),IF('Plan de Tareas'!$J18="Completada",2,1),"")) | K19: =IF(OR($D19="",$E19=""),"",IF(AND($D19<=K$7+6,$E19>=K$7),IF('Plan de Tareas'!$J18="Completada",2,1),"")) | L19: =IF(OR($D19="",$E19=""),"",IF(AND($D19<=L$7+6,$E19>=L$7),IF('Plan de Tareas'!$J18="Completada",2,1),"")) | M19: =IF(OR($D19="",$E19=""),"",IF(AND($D19<=M$7+6,$E19>=M$7),IF('Plan de Tareas'!$J18="Completada",2,1),"")) | ... AE19: =IF(OR($D19="",$E19=""),"",IF(AND($D19<=AE$7+6,$E19>=AE$7),IF('Plan de Tareas'!$J18="Completada",2,1),""))
... A127: =IF('Plan de Tareas'!$C126="","",'Plan de Tareas'!$A126) | B127: =IF('Plan de Tareas'!$C126="","",'Plan de Tareas'!$C126) | C127: =IF('Plan de Tareas'!$C126="","",'Plan de Tareas'!$D126) | D127: =IF('Plan de Tareas'!$F126="","",'Plan de Tareas'!$F126) | E127: =IF('Plan de Tareas'!$G126="","",'Plan de Tareas'!$G126) | F127: =IF(OR($D127="",$E127=""),"",IF(AND($D127<=F$7+6,$E127>=F$7),IF('Plan de Tareas'!$J126="Completada",2,1),"")) | G127: =IF(OR($D127="",$E127=""),"",IF(AND($D127<=G$7+6,$E127>=G$7),IF('Plan de Tareas'!$J126="Completada",2,1),"")) | H127: =IF(OR($D127="",$E127=""),"",IF(AND($D127<=H$7+6,$E127>=H$7),IF('Plan de Tareas'!$J126="Completada",2,1),"")) | I127: =IF(OR($D127="",$E127=""),"",IF(AND($D127<=I$7+6,$E127>=I$7),IF('Plan de Tareas'!$J126="Completada",2,1),"")) | J127: =IF(OR($D127="",$E127=""),"",IF(AND($D127<=J$7+6,$E127>=J$7),IF('Plan de Tareas'!$J126="Completada",2,1),"")) | K127: =IF(OR($D127="",$E127=""),"",IF(AND($D127<=K$7+6,$E127>=K$7),IF('Plan de Tareas'!$J126="Completada",2,1),"")) | L127: =IF(OR($D127="",$E127=""),"",IF(AND($D127<=L$7+6,$E127>=L$7),IF('Plan de Tareas'!$J126="Completada",2,1),"")) | M127: =IF(OR($D127="",$E127=""),"",IF(AND($D127<=M$7+6,$E127>=M$7),IF('Plan de Tareas'!$J126="Completada",2,1),"")) | ... AE127: =IF(OR($D127="",$E127=""),"",IF(AND($D127<=AE$7+6,$E127>=AE$7),IF('Plan de Tareas'!$J126="Completada",2,1),""))
B129: Barra naranja = tarea planeada · Barra verde = tarea completada · Columna sombreada = semana en curso

Sheet Hitos
A1: HITOS Y ENTREGABLES
A2: Puntos de control comprometidos. Un hito no tiene duración: se cumple o no se cumple.
A3: Jesús González · https://jesus-site-silk.vercel.app/
A6: # | B6: Hito / Entregable | C6: Responsable | D6: Fecha comprometida | E6: Fecha real | F6: Desviación (días) | G6: Estatus | H6: Evidencia / Comentario
A7: =IF($B7="","",ROW()-6) -> 1 | B7: Kick-off firmado con patrocinador | C7: Jesús González | D7: 46239 | F7: =IF(OR($B7="",$D7=""),"",IF($E7="",IF(TODAY()>$D7,TODAY()-$D7,0),$E7-$D7)) -> 0 | G7: =IF($B7="","",IF($E7<>"",IF($E7<=$D7,"Cumplido","Cumplido con retraso"),IF($D7="","Sin fecha",IF(TODAY()>$D7,"Vencido","Pendiente")))) -> Pendiente | H7: Minuta firmada en repositorio del proyecto
A8: =IF($B8="","",ROW()-6) | F8: =IF(OR($B8="",$D8=""),"",IF($E8="",IF(TODAY()>$D8,TODAY()-$D8,0),$E8-$D8)) | G8: =IF($B8="","",IF($E8<>"",IF($E8<=$D8,"Cumplido","Cumplido con retraso"),IF($D8="","Sin fecha",IF(TODAY()>$D8,"Vencido","Pendiente"))))
A9: =IF($B9="","",ROW()-6) | F9: =IF(OR($B9="",$D9=""),"",IF($E9="",IF(TODAY()>$D9,TODAY()-$D9,0),$E9-$D9)) | G9: =IF($B9="","",IF($E9<>"",IF($E9<=$D9,"Cumplido","Cumplido con retraso"),IF($D9="","Sin fecha",IF(TODAY()>$D9,"Vencido","Pendiente"))))
A10: =IF($B10="","",ROW()-6) | F10: =IF(OR($B10="",$D10=""),"",IF($E10="",IF(TODAY()>$D10,TODAY()-$D10,0),$E10-$D10)) | G10: =IF($B10="","",IF($E10<>"",IF($E10<=$D10,"Cumplido","Cumplido con retraso"),IF($D10="","Sin fecha",IF(TODAY()>$D10,"Vencido","Pendiente"))))
A11: =IF($B11="","",ROW()-6) | F11: =IF(OR($B11="",$D11=""),"",IF($E11="",IF(TODAY()>$D11,TODAY()-$D11,0),$E11-$D11)) | G11: =IF($B11="","",IF($E11<>"",IF($E11<=$D11,"Cumplido","Cumplido con retraso"),IF($D11="","Sin fecha",IF(TODAY()>$D11,"Vencido","Pendiente"))))
A12: =IF($B12="","",ROW()-6) | F12: =IF(OR($B12="",$D12=""),"",IF($E12="",IF(TODAY()>$D12,TODAY()-$D12,0),$E12-$D12)) | G12: =IF($B12="","",IF($E12<>"",IF($E12<=$D12,"Cumplido","Cumplido con retraso"),IF($D12="","Sin fecha",IF(TODAY()>$D12,"Vencido","Pendiente"))))
A13: =IF($B13="","",ROW()-6) | F13: =IF(OR($B13="",$D13=""),"",IF($E13="",IF(TODAY()>$D13,TODAY()-$D13,0),$E13-$D13)) | G13: =IF($B13="","",IF($E13<>"",IF($E13<=$D13,"Cumplido","Cumplido con retraso"),IF($D13="","Sin fecha",IF(TODAY()>$D13,"Vencido","Pendiente"))))
A14: =IF($B14="","",ROW()-6) | F14: =IF(OR($B14="",$D14=""),"",IF($E14="",IF(TODAY()>$D14,TODAY()-$D14,0),$E14-$D14)) | G14: =IF($B14="","",IF($E14<>"",IF($E14<=$D14,"Cumplido","Cumplido con retraso"),IF($D14="","Sin fecha",IF(TODAY()>$D14,"Vencido","Pendiente"))))
A15: =IF($B15="","",ROW()-6) | F15: =IF(OR($B15="",$D15=""),"",IF($E15="",IF(TODAY()>$D15,TODAY()-$D15,0),$E15-$D15)) | G15: =IF($B15="","",IF($E15<>"",IF($E15<=$D15,"Cumplido","Cumplido con retraso"),IF($D15="","Sin fecha",IF(TODAY()>$D15,"Vencido","Pendiente"))))
A16: =IF($B16="","",ROW()-6) | F16: =IF(OR($B16="",$D16=""),"",IF($E16="",IF(TODAY()>$D16,TODAY()-$D16,0),$E16-$D16)) | G16: =IF($B16="","",IF($E16<>"",IF($E16<=$D16,"Cumplido","Cumplido con retraso"),IF($D16="","Sin fecha",IF(TODAY()>$D16,"Vencido","Pendiente"))))
A17: =IF($B17="","",ROW()-6) | F17: =IF(OR($B17="",$D17=""),"",IF($E17="",IF(TODAY()>$D17,TODAY()-$D17,0),$E17-$D17)) | G17: =IF($B17="","",IF($E17<>"",IF($E17<=$D17,"Cumplido","Cumplido con retraso"),IF($D17="","Sin fecha",IF(TODAY()>$D17,"Vencido","Pendiente"))))
A18: =IF($B18="","",ROW()-6) | F18: =IF(OR($B18="",$D18=""),"",IF($E18="",IF(TODAY()>$D18,TODAY()-$D18,0),$E18-$D18)) | G18: =IF($B18="","",IF($E18<>"",IF($E18<=$D18,"Cumplido","Cumplido con retraso"),IF($D18="","Sin fecha",IF(TODAY()>$D18,"Vencido","Pendiente"))))
A19: =IF($B19="","",ROW()-6) | F19: =IF(OR($B19="",$D19=""),"",IF($E19="",IF(TODAY()>$D19,TODAY()-$D19,0),$E19-$D19)) | G19: =IF($B19="","",IF($E19<>"",IF($E19<=$D19,"Cumplido","Cumplido con retraso"),IF($D19="","Sin fecha",IF(TODAY()>$D19,"Vencido","Pendiente"))))
... A37: =IF($B37="","",ROW()-6) | F37: =IF(OR($B37="",$D37=""),"",IF($E37="",IF(TODAY()>$D37,TODAY()-$D37,0),$E37-$D37)) | G37: =IF($B37="","",IF($E37<>"",IF($E37<=$D37,"Cumplido","Cumplido con retraso"),IF($D37="","Sin fecha",IF(TODAY()>$D37,"Vencido","Pendiente"))))

Sheet Riesgos
A1: MATRIZ DE RIESGOS
A2: Probabilidad × Impacto define la severidad. Todo riesgo Crítico o Alto necesita dueño y fecha.
A3: Jesús González · https://jesus-site-silk.vercel.app/
A6: ID | B6: Riesgo identificado | C6: Categoría | D6: Probabilidad | E6: Impacto | F6: Severidad | G6: Nivel | H6: Estrategia | I6: Plan de mitigación | J6: Dueño | K6: Fecha límite | L6: Estatus
A7: =IF($B7="","",ROW()-6) -> 1 | B7: Los usuarios clave no liberan tiempo para las sesiones de requerimientos | C7: Organizacional | D7: Alto | E7: Alto | F7: =IF(OR($B7="",$D7="",$E7=""),"",IF($D7="Alto",3,IF($D7="Medio",2,1))*IF($E7="Alto",3,IF($E7="Medio",2,1))) -> 9 | G7: =IF($F7="","",IF($F7>=6,"Crítico",IF($F7>=4,"Alto",IF($F7>=2,"Medio","Bajo")))) -> Crítico | H7: Mitigar | I7: Bloquear agenda con 3 semanas de anticipación y escalar al patrocinador si no hay confirmación | J7: Jesús González | K7: 46241 | L7: Abierto
A8: =IF($B8="","",ROW()-6) | F8: =IF(OR($B8="",$D8="",$E8=""),"",IF($D8="Alto",3,IF($D8="Medio",2,1))*IF($E8="Alto",3,IF($E8="Medio",2,1))) | G8: =IF($F8="","",IF($F8>=6,"Crítico",IF($F8>=4,"Alto",IF($F8>=2,"Medio","Bajo"))))
A9: =IF($B9="","",ROW()-6) | F9: =IF(OR($B9="",$D9="",$E9=""),"",IF($D9="Alto",3,IF($D9="Medio",2,1))*IF($E9="Alto",3,IF($E9="Medio",2,1))) | G9: =IF($F9="","",IF($F9>=6,"Crítico",IF($F9>=4,"Alto",IF($F9>=2,"Medio","Bajo"))))
A10: =IF($B10="","",ROW()-6) | F10: =IF(OR($B10="",$D10="",$E10=""),"",IF($D10="Alto",3,IF($D10="Medio",2,1))*IF($E10="Alto",3,IF($E10="Medio",2,1))) | G10: =IF($F10="","",IF($F10>=6,"Crítico",IF($F10>=4,"Alto",IF($F10>=2,"Medio","Bajo"))))
A11: =IF($B11="","",ROW()-6) | F11: =IF(OR($B11="",$D11="",$E11=""),"",IF($D11="Alto",3,IF($D11="Medio",2,1))*IF($E11="Alto",3,IF($E11="Medio",2,1))) | G11: =IF($F11="","",IF($F11>=6,"Crítico",IF($F11>=4,"Alto",IF($F11>=2,"Medio","Bajo"))))
A12: =IF($B12="","",ROW()-6) | F12: =IF(OR($B12="",$D12="",$E12=""),"",IF($D12="Alto",3,IF($D12="Medio",2,1))*IF($E12="Alto",3,IF($E12="Medio",2,1))) | G12: =IF($F12="","",IF($F12>=6,"Crítico",IF($F12>=4,"Alto",IF($F12>=2,"Medio","Bajo"))))
A13: =IF($B13="","",ROW()-6) | F13: =IF(OR($B13="",$D13="",$E13=""),"",IF($D13="Alto",3,IF($D13="Medio",2,1))*IF($E13="Alto",3,IF($E13="Medio",2,1))) | G13: =IF($F13="","",IF($F13>=6,"Crítico",IF($F13>=4,"Alto",IF($F13>=2,"Medio","Bajo"))))
A14: =IF($B14="","",ROW()-6) | F14: =IF(OR($B14="",$D14="",$E14=""),"",IF($D14="Alto",3,IF($D14="Medio",2,1))*IF($E14="Alto",3,IF($E14="Medio",2,1))) | G14: =IF($F14="","",IF($F14>=6,"Crítico",IF($F14>=4,"Alto",IF($F14>=2,"Medio","Bajo"))))
A15: =IF($B15="","",ROW()-6) | F15: =IF(OR($B15="",$D15="",$E15=""),"",IF($D15="Alto",3,IF($D15="Medio",2,1))*IF($E15="Alto",3,IF($E15="Medio",2,1))) | G15: =IF($F15="","",IF($F15>=6,"Crítico",IF($F15>=4,"Alto",IF($F15>=2,"Medio","Bajo"))))
A16: =IF($B16="","",ROW()-6) | F16: =IF(OR($B16="",$D16="",$E16=""),"",IF($D16="Alto",3,IF($D16="Medio",2,1))*IF($E16="Alto",3,IF($E16="Medio",2,1))) | G16: =IF($F16="","",IF($F16>=6,"Crítico",IF($F16>=4,"Alto",IF($F16>=2,"Medio","Bajo"))))
A17: =IF($B17="","",ROW()-6) | F17: =IF(OR($B17="",$D17="",$E17=""),"",IF($D17="Alto",3,IF($D17="Medio",2,1))*IF($E17="Alto",3,IF($E17="Medio",2,1))) | G17: =IF($F17="","",IF($F17>=6,"Crítico",IF($F17>=4,"Alto",IF($F17>=2,"Medio","Bajo"))))
A18: =IF($B18="","",ROW()-6) | F18: =IF(OR($B18="",$D18="",$E18=""),"",IF($D18="Alto",3,IF($D18="Medio",2,1))*IF($E18="Alto",3,IF($E18="Medio",2,1))) | G18: =IF($F18="","",IF($F18>=6,"Crítico",IF($F18>=4,"Alto",IF($F18>=2,"Medio","Bajo"))))
A19: =IF($B19="","",ROW()-6) | F19: =IF(OR($B19="",$D19="",$E19=""),"",IF($D19="Alto",3,IF($D19="Medio",2,1))*IF($E19="Alto",3,IF($E19="Medio",2,1))) | G19: =IF($F19="","",IF($F19>=6,"Crítico",IF($F19>=4,"Alto",IF($F19>=2,"Medio","Bajo"))))
... A47: =IF($B47="","",ROW()-6) | F47: =IF(OR($B47="",$D47="",$E47=""),"",IF($D47="Alto",3,IF($D47="Medio",2,1))*IF($E47="Alto",3,IF($E47="Medio",2,1))) | G47: =IF($F47="","",IF($F47>=6,"Crítico",IF($F47>=4,"Alto",IF($F47>=2,"Medio","Bajo"))))

Sheet Interesados
A1: MAPA DE INTERESADOS
A2: Poder × Interés define cómo tratar a cada actor. El campo de estrategia se calcula solo.
A3: Jesús González · https://jesus-site-silk.vercel.app/
A6: # | B6: Nombre | C6: Cargo / Área | D6: Rol en el proyecto | E6: Poder | F6: Interés | G6: Cuadrante | H6: Estrategia sugerida | I6: Compromiso / Notas
A7: =IF($B7="","",ROW()-6) -> 1 | B7: Nombre del patrocinador | C7: Dirección de Operaciones | D7: Patrocinador | E7: Alto | F7: Alto | G7: =IF(OR($B7="",$E7="",$F7=""),"",IF($E7="Alto",IF($F7="Alto","Gestionar de cerca","Mantener satisfecho"),IF($F7="Alto","Mantener informado","Monitorear"))) -> Gestionar de cerca | H7: =IF($G7="","",IF($G7="Gestionar de cerca","Involucrar en decisiones y reportar semanalmente",IF($G7="Mantener satisfecho","Consultar antes de decidir; evitar sorpresas",IF($G7="Mantener informado","Enviar avances periódicos; aprovechar como aliado","Comunicación mínima; revisar si cambia su posición")))) -> Involucrar en decisiones y reportar semanalmente | I7: Revisión quincenal de 30 min; le importa el impacto en costo operativo
A8: =IF($B8="","",ROW()-6) | G8: =IF(OR($B8="",$E8="",$F8=""),"",IF($E8="Alto",IF($F8="Alto","Gestionar de cerca","Mantener satisfecho"),IF($F8="Alto","Mantener informado","Monitorear"))) | H8: =IF($G8="","",IF($G8="Gestionar de cerca","Involucrar en decisiones y reportar semanalmente",IF($G8="Mantener satisfecho","Consultar antes de decidir; evitar sorpresas",IF($G8="Mantener informado","Enviar avances periódicos; aprovechar como aliado","Comunicación mínima; revisar si cambia su posición"))))
A9: =IF($B9="","",ROW()-6) | G9: =IF(OR($B9="",$E9="",$F9=""),"",IF($E9="Alto",IF($F9="Alto","Gestionar de cerca","Mantener satisfecho"),IF($F9="Alto","Mantener informado","Monitorear"))) | H9: =IF($G9="","",IF($G9="Gestionar de cerca","Involucrar en decisiones y reportar semanalmente",IF($G9="Mantener satisfecho","Consultar antes de decidir; evitar sorpresas",IF($G9="Mantener informado","Enviar avances periódicos; aprovechar como aliado","Comunicación mínima; revisar si cambia su posición"))))
A10: =IF($B10="","",ROW()-6) | G10: =IF(OR($B10="",$E10="",$F10=""),"",IF($E10="Alto",IF($F10="Alto","Gestionar de cerca","Mantener satisfecho"),IF($F10="Alto","Mantener informado","Monitorear"))) | H10: =IF($G10="","",IF($G10="Gestionar de cerca","Involucrar en decisiones y reportar semanalmente",IF($G10="Mantener satisfecho","Consultar antes de decidir; evitar sorpresas",IF($G10="Mantener informado","Enviar avances periódicos; aprovechar como aliado","Comunicación mínima; revisar si cambia su posición"))))
A11: =IF($B11="","",ROW()-6) | G11: =IF(OR($B11="",$E11="",$F11=""),"",IF($E11="Alto",IF($F11="Alto","Gestionar de cerca","Mantener satisfecho"),IF($F11="Alto","Mantener informado","Monitorear"))) | H11: =IF($G11="","",IF($G11="Gestionar de cerca","Involucrar en decisiones y reportar semanalmente",IF($G11="Mantener satisfecho","Consultar antes de decidir; evitar sorpresas",IF($G11="Mantener informado","Enviar avances periódicos; aprovechar como aliado","Comunicación mínima; revisar si cambia su posición"))))
A12: =IF($B12="","",ROW()-6) | G12: =IF(OR($B12="",$E12="",$F12=""),"",IF($E12="Alto",IF($F12="Alto","Gestionar de cerca","Mantener satisfecho"),IF($F12="Alto","Mantener informado","Monitorear"))) | H12: =IF($G12="","",IF($G12="Gestionar de cerca","Involucrar en decisiones y reportar semanalmente",IF($G12="Mantener satisfecho","Consultar antes de decidir; evitar sorpresas",IF($G12="Mantener informado","Enviar avances periódicos; aprovechar como aliado","Comunicación mínima; revisar si cambia su posición"))))
A13: =IF($B13="","",ROW()-6) | G13: =IF(OR($B13="",$E13="",$F13=""),"",IF($E13="Alto",IF($F13="Alto","Gestionar de cerca","Mantener satisfecho"),IF($F13="Alto","Mantener informado","Monitorear"))) | H13: =IF($G13="","",IF($G13="Gestionar de cerca","Involucrar en decisiones y reportar semanalmente",IF($G13="Mantener satisfecho","Consultar antes de decidir; evitar sorpresas",IF($G13="Mantener informado","Enviar avances periódicos; aprovechar como aliado","Comunicación mínima; revisar si cambia su posición"))))
A14: =IF($B14="","",ROW()-6) | G14: =IF(OR($B14="",$E14="",$F14=""),"",IF($E14="Alto",IF($F14="Alto","Gestionar de cerca","Mantener satisfecho"),IF($F14="Alto","Mantener informado","Monitorear"))) | H14: =IF($G14="","",IF($G14="Gestionar de cerca","Involucrar en decisiones y reportar semanalmente",IF($G14="Mantener satisfecho","Consultar antes de decidir; evitar sorpresas",IF($G14="Mantener informado","Enviar avances periódicos; aprovechar como aliado","Comunicación mínima; revisar si cambia su posición"))))
A15: =IF($B15="","",ROW()-6) | G15: =IF(OR($B15="",$E15="",$F15=""),"",IF($E15="Alto",IF($F15="Alto","Gestionar de cerca","Mantener satisfecho"),IF($F15="Alto","Mantener informado","Monitorear"))) | H15: =IF($G15="","",IF($G15="Gestionar de cerca","Involucrar en decisiones y reportar semanalmente",IF($G15="Mantener satisfecho","Consultar antes de decidir; evitar sorpresas",IF($G15="Mantener informado","Enviar avances periódicos; aprovechar como aliado","Comunicación mínima; revisar si cambia su posición"))))
A16: =IF($B16="","",ROW()-6) | G16: =IF(OR($B16="",$E16="",$F16=""),"",IF($E16="Alto",IF($F16="Alto","Gestionar de cerca","Mantener satisfecho"),IF($F16="Alto","Mantener informado","Monitorear"))) | H16: =IF($G16="","",IF($G16="Gestionar de cerca","Involucrar en decisiones y reportar semanalmente",IF($G16="Mantener satisfecho","Consultar antes de decidir; evitar sorpresas",IF($G16="Mantener informado","Enviar avances periódicos; aprovechar como aliado","Comunicación mínima; revisar si cambia su posición"))))
A17: =IF($B17="","",ROW()-6) | G17: =IF(OR($B17="",$E17="",$F17=""),"",IF($E17="Alto",IF($F17="Alto","Gestionar de cerca","Mantener satisfecho"),IF($F17="Alto","Mantener informado","Monitorear"))) | H17: =IF($G17="","",IF($G17="Gestionar de cerca","Involucrar en decisiones y reportar semanalmente",IF($G17="Mantener satisfecho","Consultar antes de decidir; evitar sorpresas",IF($G17="Mantener informado","Enviar avances periódicos; aprovechar como aliado","Comunicación mínima; revisar si cambia su posición"))))
A18: =IF($B18="","",ROW()-6) | G18: =IF(OR($B18="",$E18="",$F18=""),"",IF($E18="Alto",IF($F18="Alto","Gestionar de cerca","Mantener satisfecho"),IF($F18="Alto","Mantener informado","Monitorear"))) | H18: =IF($G18="","",IF($G18="Gestionar de cerca","Involucrar en decisiones y reportar semanalmente",IF($G18="Mantener satisfecho","Consultar antes de decidir; evitar sorpresas",IF($G18="Mantener informado","Enviar avances periódicos; aprovechar como aliado","Comunicación mínima; revisar si cambia su posición"))))
A19: =IF($B19="","",ROW()-6) | G19: =IF(OR($B19="",$E19="",$F19=""),"",IF($E19="Alto",IF($F19="Alto","Gestionar de cerca","Mantener satisfecho"),IF($F19="Alto","Mantener informado","Monitorear"))) | H19: =IF($G19="","",IF($G19="Gestionar de cerca","Involucrar en decisiones y reportar semanalmente",IF($G19="Mantener satisfecho","Consultar antes de decidir; evitar sorpresas",IF($G19="Mantener informado","Enviar avances periódicos; aprovechar como aliado","Comunicación mínima; revisar si cambia su posición"))))
... A32: =IF($B32="","",ROW()-6) | G32: =IF(OR($B32="",$E32="",$F32=""),"",IF($E32="Alto",IF($F32="Alto","Gestionar de cerca","Mantener satisfecho"),IF($F32="Alto","Mantener informado","Monitorear"))) | H32: =IF($G32="","",IF($G32="Gestionar de cerca","Involucrar en decisiones y reportar semanalmente",IF($G32="Mantener satisfecho","Consultar antes de decidir; evitar sorpresas",IF($G32="Mantener informado","Enviar avances periódicos; aprovechar como aliado","Comunicación mínima; revisar si cambia su posición"))))

Sheet Presupuesto
A1: PRESUPUESTO
A2: Planeado contra ejercido. La desviación y el semáforo se calculan solos.
A3: Jesús González · https://jesus-site-silk.vercel.app/
A6: # | B6: Concepto | C6: Categoría | D6: Responsable | E6: Monto planeado | F6: Monto ejercido | G6: Comprometido | H6: Desviación | I6: % Ejecutado
A7: =IF($B7="","",ROW()-6) -> 1 | B7: Licencias de plataforma analítica (12 meses) | C7: Licencias | D7: Jesús González | E7: 480000 | F7: 120000 | G7: 0 | H7: =IF($B7="","",$E7-$F7-$G7) -> 360000 | I7: =IF(OR($B7="",$E7=0,$E7=""),"",($F7+$G7)/$E7) -> 0.25
A8: =IF($B8="","",ROW()-6) | H8: =IF($B8="","",$E8-$F8-$G8) | I8: =IF(OR($B8="",$E8=0,$E8=""),"",($F8+$G8)/$E8)
A9: =IF($B9="","",ROW()-6) | H9: =IF($B9="","",$E9-$F9-$G9) | I9: =IF(OR($B9="",$E9=0,$E9=""),"",($F9+$G9)/$E9)
A10: =IF($B10="","",ROW()-6) | H10: =IF($B10="","",$E10-$F10-$G10) | I10: =IF(OR($B10="",$E10=0,$E10=""),"",($F10+$G10)/$E10)
A11: =IF($B11="","",ROW()-6) | H11: =IF($B11="","",$E11-$F11-$G11) | I11: =IF(OR($B11="",$E11=0,$E11=""),"",($F11+$G11)/$E11)
A12: =IF($B12="","",ROW()-6) | H12: =IF($B12="","",$E12-$F12-$G12) | I12: =IF(OR($B12="",$E12=0,$E12=""),"",($F12+$G12)/$E12)
A13: =IF($B13="","",ROW()-6) | H13: =IF($B13="","",$E13-$F13-$G13) | I13: =IF(OR($B13="",$E13=0,$E13=""),"",($F13+$G13)/$E13)
A14: =IF($B14="","",ROW()-6) | H14: =IF($B14="","",$E14-$F14-$G14) | I14: =IF(OR($B14="",$E14=0,$E14=""),"",($F14+$G14)/$E14)
A15: =IF($B15="","",ROW()-6) | H15: =IF($B15="","",$E15-$F15-$G15) | I15: =IF(OR($B15="",$E15=0,$E15=""),"",($F15+$G15)/$E15)
A16: =IF($B16="","",ROW()-6) | H16: =IF($B16="","",$E16-$F16-$G16) | I16: =IF(OR($B16="",$E16=0,$E16=""),"",($F16+$G16)/$E16)
A17: =IF($B17="","",ROW()-6) | H17: =IF($B17="","",$E17-$F17-$G17) | I17: =IF(OR($B17="",$E17=0,$E17=""),"",($F17+$G17)/$E17)
A18: =IF($B18="","",ROW()-6) | H18: =IF($B18="","",$E18-$F18-$G18) | I18: =IF(OR($B18="",$E18=0,$E18=""),"",($F18+$G18)/$E18)
A19: =IF($B19="","",ROW()-6) | H19: =IF($B19="","",$E19-$F19-$G19) | I19: =IF(OR($B19="",$E19=0,$E19=""),"",($F19+$G19)/$E19)
... A42: =IF($B42="","",ROW()-6) | H42: =IF($B42="","",$E42-$F42-$G42) | I42: =IF(OR($B42="",$E42=0,$E42=""),"",($F42+$G42)/$E42)
D43: TOTALES | E43: =SUM(E7:E42) -> 480000 | F43: =SUM(F7:F42) -> 120000 | G43: =SUM(G7:G42) -> 0 | H43: =SUM(H7:H42) -> 360000 | I43: =IF($E43=0,"",($F43+$G43)/$E43) -> 0.25
B45: Nota: 'Comprometido' es gasto ya autorizado que aún no se paga. Desviación negativa = sobregiro.

Sheet Equipo
A1: EQUIPO Y RECURSOS
A2: Da de alta al equipo aquí. El costo por hora alimenta el cálculo de esfuerzo del proyecto.
A3: Jesús González · https://jesus-site-silk.vercel.app/
A6: # | B6: Nombre | C6: Rol | D6: Área / Empresa | E6: Contacto | F6: Costo hora | G6: % Asignación | H6: Costo mensual estimado
A7: 1 | B7: Jesús González | C7: Líder de proyecto | D7: Dirección de Datos | E7: correo@dominio.com | F7: 850 | G7: 0.5 | H7: =IF(OR($B7="",$F7=""),"",$F7*160*$G7) -> 68000
A8: 2 | B8: Recurso 2 | C8: Analista de datos | D8: Dirección de Datos | F8: 450 | G8: 1 | H8: =IF(OR($B8="",$F8=""),"",$F8*160*$G8) -> 72000
A9: 3 | H9: =IF(OR($B9="",$F9=""),"",$F9*160*$G9)
A10: 4 | H10: =IF(OR($B10="",$F10=""),"",$F10*160*$G10)
A11: 5 | H11: =IF(OR($B11="",$F11=""),"",$F11*160*$G11)
A12: 6 | H12: =IF(OR($B12="",$F12=""),"",$F12*160*$G12)
A13: 7 | H13: =IF(OR($B13="",$F13=""),"",$F13*160*$G13)
A14: 8 | H14: =IF(OR($B14="",$F14=""),"",$F14*160*$G14)
A15: 9 | H15: =IF(OR($B15="",$F15=""),"",$F15*160*$G15)
A16: 10 | H16: =IF(OR($B16="",$F16=""),"",$F16*160*$G16)
A17: 11 | H17: =IF(OR($B17="",$F17=""),"",$F17*160*$G17)
A18: 12 | H18: =IF(OR($B18="",$F18=""),"",$F18*160*$G18)
A19: 13 | H19: =IF(OR($B19="",$F19=""),"",$F19*160*$G19)
A20: 14 | H20: =IF(OR($B20="",$F20=""),"",$F20*160*$G20)
... A47: 41 | H47: =IF(OR($B47="",$F47=""),"",$F47*160*$G47)
E49: TOTAL EQUIPO | H49: =SUM(H7:H47) -> 140000
E50: Supuesto: 160 horas hábiles por mes. Cámbialo en la fórmula de la columna H si tu base es distinta.

Sheet Decisiones
A1: BITÁCORA DE DECISIONES
A2: Registra qué se decidió, quién decidió y por qué. En seis meses nadie recuerda el porqué.
A3: Jesús González · https://jesus-site-silk.vercel.app/
A6: # | B6: Fecha | C6: Decisión tomada | D6: Contexto / Alternativas descartadas | E6: Quién decidió | F6: Impacto | G6: Reversible
A7: =IF($C7="","",ROW()-6) -> 1 | B7: 46234 | C7: Se usará la plataforma existente en vez de licenciar una nueva herramienta | D7: Se evaluaron 3 opciones; se descartó la compra por tiempo de procuración (>4 meses) | E7: Jesús González | F7: Ahorro de 4 meses en el cronograma | G7: Costosa de revertir
A8: =IF($C8="","",ROW()-6)
A9: =IF($C9="","",ROW()-6)
A10: =IF($C10="","",ROW()-6)
A11: =IF($C11="","",ROW()-6)
A12: =IF($C12="","",ROW()-6)
A13: =IF($C13="","",ROW()-6)
A14: =IF($C14="","",ROW()-6)
A15: =IF($C15="","",ROW()-6)
A16: =IF($C16="","",ROW()-6)
A17: =IF($C17="","",ROW()-6)
A18: =IF($C18="","",ROW()-6)
A19: =IF($C19="","",ROW()-6)
... A37: =IF($C37="","",ROW()-6)

Sheet Incidencias
A1: REGISTRO DE INCIDENCIAS
A2: Problemas que ya ocurrieron. Un riesgo materializado se convierte en incidencia.
A3: Jesús González · https://jesus-site-silk.vercel.app/
A6: # | B6: Fecha detección | C6: Incidencia | D6: Origen | E6: Severidad | F6: Responsable | G6: Acción correctiva | H6: Estatus | I6: Días abierta
A7: =IF($C7="","",ROW()-6) -> 1 | B7: 46234 | C7: El extracto de origen llega incompleto los lunes | D7: Sistema fuente | E7: Medio | F7: Recurso 2 | G7: Se agregó validación de conteo y reintento automático | H7: En análisis | I7: =IF(OR($C7="",$B7=""),"",IF($H7="Resuelta","-",TODAY()-$B7)) -> -1
A8: =IF($C8="","",ROW()-6) | I8: =IF(OR($C8="",$B8=""),"",IF($H8="Resuelta","-",TODAY()-$B8))
A9: =IF($C9="","",ROW()-6) | I9: =IF(OR($C9="",$B9=""),"",IF($H9="Resuelta","-",TODAY()-$B9))
A10: =IF($C10="","",ROW()-6) | I10: =IF(OR($C10="",$B10=""),"",IF($H10="Resuelta","-",TODAY()-$B10))
A11: =IF($C11="","",ROW()-6) | I11: =IF(OR($C11="",$B11=""),"",IF($H11="Resuelta","-",TODAY()-$B11))
A12: =IF($C12="","",ROW()-6) | I12: =IF(OR($C12="",$B12=""),"",IF($H12="Resuelta","-",TODAY()-$B12))
A13: =IF($C13="","",ROW()-6) | I13: =IF(OR($C13="",$B13=""),"",IF($H13="Resuelta","-",TODAY()-$B13))
A14: =IF($C14="","",ROW()-6) | I14: =IF(OR($C14="",$B14=""),"",IF($H14="Resuelta","-",TODAY()-$B14))
A15: =IF($C15="","",ROW()-6) | I15: =IF(OR($C15="",$B15=""),"",IF($H15="Resuelta","-",TODAY()-$B15))
A16: =IF($C16="","",ROW()-6) | I16: =IF(OR($C16="",$B16=""),"",IF($H16="Resuelta","-",TODAY()-$B16))
A17: =IF($C17="","",ROW()-6) | I17: =IF(OR($C17="",$B17=""),"",IF($H17="Resuelta","-",TODAY()-$B17))
A18: =IF($C18="","",ROW()-6) | I18: =IF(OR($C18="",$B18=""),"",IF($H18="Resuelta","-",TODAY()-$B18))
A19: =IF($C19="","",ROW()-6) | I19: =IF(OR($C19="",$B19=""),"",IF($H19="Resuelta","-",TODAY()-$B19))
... A37: =IF($C37="","",ROW()-6) | I37: =IF(OR($C37="",$B37=""),"",IF($H37="Resuelta","-",TODAY()-$B37))

Sheet Listas
A1: LISTAS Y CATÁLOGOS
A2: Edita estos catálogos primero: alimentan las listas desplegables de todo el libro.
A3: Jesús González · https://jesus-site-silk.vercel.app/
A5: Puedes agregar valores debajo de cada catálogo (hasta la fila 30) y aparecerán en los desplegables.
A6: Estado tarea | B6: Prioridad | C6: Nivel | D6: Fase | E6: Responsable | F6: Categoría gasto | G6: Estatus riesgo | H6: Estrategia riesgo | I6: Estatus incidencia
A7: No iniciada | B7: Alta | C7: Alto | D7: Inicio | E7: Jesús González | F7: Personal | G7: Abierto | H7: Evitar | I7: Abierta
A8: En curso | B8: Media | C8: Medio | D8: Planeación | E8: Recurso 2 | F8: Licencias | G8: En mitigación | H8: Mitigar | I8: En análisis
A9: Bloqueada | B9: Baja | C9: Bajo | D9: Diseño | E9: Recurso 3 | F9: Infraestructura | G9: Materializado | H9: Transferir | I9: Resuelta
A10: Completada | D10: Construcción | E10: Recurso 4 | F10: Consultoría | G10: Cerrado | H10: Aceptar | I10: Escalada
A11: Cancelada | D11: Pruebas | E11: Recurso 5 | F11: Capacitación
D12: Despliegue | E12: Por asignar | F12: Viáticos
D13: Cierre | F13: Otros
